extra_geom/__init__.py
extra_geom/base.py
extra_geom/crystfel_fmt.py
extra_geom/detectors.py
extra_geom/lpd_old.py
extra_geom/motors.py
extra_geom/pyfai.py
extra_geom/snapped.py
extra_geom/tests/__init__.py
extra_geom/tests/dssc_geo_june19.h5
extra_geom/tests/lpd_mar_18.h5
extra_geom/tests/test_agipd500k2g_geometry.py
extra_geom/tests/test_agipd_geometry.py
extra_geom/tests/test_dssc_geometry.py
extra_geom/tests/test_epix_geometry.py
extra_geom/tests/test_generic_geometry.py
extra_geom/tests/test_geometry_old.py
extra_geom/tests/test_jungfrau_geometry.py
extra_geom/tests/test_lpd_geometry.py
extra_geom/tests/test_lpdmini_geometry.py
extra_geom/tests/test_motors.py
extra_geom/tests/test_pnccd_geometry.py
extra_geom/tests/utils.py
extra_geom-1.15.0.dist-info/licenses/LICENSE
extra_geom-1.15.0.dist-info/METADATA
extra_geom-1.15.0.dist-info/WHEEL
extra_geom-1.15.0.dist-info/top_level.txt
extra_geom-1.15.0.dist-info/RECORD
