Metadata-Version: 2.4
Name: EXtra-geom
Version: 1.15.0
Summary: Tools to work with EuXFEL detector geometry and assemble detector images
Home-page: https://github.com/European-XFEL/EXtra-geom
Author: European XFEL GmbH
Author-email: da-support@xfel.eu
Maintainer: Thomas Michelat
License: BSD-3-Clause
Project-URL: Documentation, https://extra-geom.readthedocs.io/en/latest/
Project-URL: Changelog, https://extra-geom.readthedocs.io/en/latest/changelog.html
Classifier: Intended Audience :: Developers
Classifier: Intended Audience :: Science/Research
Classifier: License :: OSI Approved :: BSD License
Classifier: Programming Language :: Python :: 3
Classifier: Topic :: Scientific/Engineering :: Information Analysis
Classifier: Topic :: Scientific/Engineering :: Physics
Requires-Python: >=3.10
License-File: LICENSE
Requires-Dist: cfel_fmt<3.0,>=2.0
Requires-Dist: h5py>=2.7.1
Requires-Dist: matplotlib
Requires-Dist: numpy
Provides-Extra: interpolate
Requires-Dist: scipy; extra == "interpolate"
Provides-Extra: docs
Requires-Dist: sphinx>=4.3; extra == "docs"
Requires-Dist: nbsphinx; extra == "docs"
Requires-Dist: ipython; extra == "docs"
Requires-Dist: sphinxcontrib_github_alt; extra == "docs"
Requires-Dist: sphinx-rtd-theme>=1.2; extra == "docs"
Requires-Dist: Jinja2<3.1.0; extra == "docs"
Provides-Extra: test
Requires-Dist: pytest; extra == "test"
Requires-Dist: pytest-cov; extra == "test"
Requires-Dist: coverage; extra == "test"
Requires-Dist: nbval; extra == "test"
Requires-Dist: testpath; extra == "test"
Requires-Dist: xarray; extra == "test"
Requires-Dist: EXtra-data; extra == "test"
Requires-Dist: pyFAI; extra == "test"
Requires-Dist: condat_gridconv; extra == "test"
Dynamic: author
Dynamic: author-email
Dynamic: classifier
Dynamic: description
Dynamic: description-content-type
Dynamic: home-page
Dynamic: license
Dynamic: license-file
Dynamic: maintainer
Dynamic: project-url
Dynamic: provides-extra
Dynamic: requires-dist
Dynamic: requires-python
Dynamic: summary
